<?xml version="1.0" encoding="utf-8"?>
<dataController name="Qstpurdtl" conflictDetection="overwriteChanges" label="Qstpurdtl" plugIn="eZee.Data.AnnotationPlugIn" xmlns="urn:schemas-codeontime-com:data-aquarium">
  <commands>
    <command id="command1" type="Text">
      <text><![CDATA[
select
	"Qstpurdtl"."Cstm_No" "Cstm_No"
	,"Qstpurdtl"."Brn_No" "Brn_No"
	,"Qstpurdtl"."Doc_Ty" "Doc_Ty"
	,"Qstpurdtl"."Doc_No" "Doc_No"
	,"Qstpurdtl"."Ln_No" "Ln_No"
	,"Qstpurdtl"."Itm_No" "Itm_No"
	,"Qstpurdtl"."ITEM" "ITEM"
	,"Qstpurdtl"."Unit_No" "Unit_No"
	,"Qstpurdtl"."UnitPrice" "UnitPrice"
	,"Qstpurdtl"."Quantity" "Quantity"
	,"Qstpurdtl"."Discount" "Discount"
	,"Qstpurdtl"."Titm_Sal" "Titm_Sal"
	,"Qstpurdtl"."Titm_Cost" "Titm_Cost"
	,"Qstpurdtl"."Itm_Cost" "Itm_Cost"
	,"Qstpurdtl"."Catg_No" "Catg_No"
	,"Qstpurdtl"."Sup_No" "Sup_No"
	,"Qstpurdtl"."notesdtl" "notesdtl"
	,"Qstpurdtl"."User_Id" "User_Id"
	,"Qstpurdtl"."Idate" "Idate"
	,"Qstpurdtl"."Post" "Post"
	,"Qstpurdtl"."submit" "submit"
	,"Qstpurdtl"."Cstm_NM" "Cstm_NM"
	,"Qstpurdtl"."flat" "flat"
from "dbo"."Qstpurdtl" "Qstpurdtl"
]]></text>
    </command>
    <command id="Doc_NoIdentityCommand" type="Text" event="Inserted">
      <text><![CDATA[select @@identity]]></text>
      <output>
        <fieldOutput fieldName="Doc_No" />
      </output>
    </command>
  </commands>
  <fields>
    <field name="Cstm_No" type="Int64" label="Cstm No" showInSummary="true" />
    <field name="Brn_No" type="Int64" label="Brn No" showInSummary="true" />
    <field name="Doc_Ty" type="Int32" allowNulls="false" label="Doc Ty" readOnly="true" showInSummary="true" />
    <field name="Doc_No" type="Int64" allowNulls="false" label="Doc No" readOnly="true" showInSummary="true" />
    <field name="Ln_No" type="Int64" allowNulls="false" label="Ln No" showInSummary="true" />
    <field name="Itm_No" type="Int64" label="Itm No" />
    <field name="ITEM" type="String" label="Item" length="255" />
    <field name="Unit_No" type="Int64" label="Unit No" />
    <field name="UnitPrice" type="Decimal" label="Unit Price" readOnly="true" />
    <field name="Quantity" type="Decimal" label="Quantity" />
    <field name="Discount" type="Int64" label="Discount" />
    <field name="Titm_Sal" type="Decimal" label="Titm Sal" readOnly="true" />
    <field name="Titm_Cost" type="Decimal" label="Titm Cost" />
    <field name="Itm_Cost" type="Decimal" label="Itm Cost" />
    <field name="Catg_No" type="Int32" allowNulls="false" label="Catg No" readOnly="true" />
    <field name="Sup_No" type="Int32" allowNulls="false" label="Sup No" readOnly="true" />
    <field name="notesdtl" type="String" label="Notesdtl" length="255" />
    <field name="User_Id" type="Int32" allowNulls="false" label="User#" readOnly="true" />
    <field name="Idate" type="DateTime" label="Idate" />
    <field name="Post" type="Byte" label="Post" />
    <field name="submit" type="Int64" label="Submit" />
    <field name="Cstm_NM" type="String" label="Cstm NM" length="255" />
    <field name="flat" type="Int64" label="Flat" />
  </fields>
  <views>
    <view id="grid1" type="Grid" commandId="command1" label="Qstpurdtl">
      <headerText>$DefaultGridViewDescription</headerText>
      <dataFields>
        <dataField fieldName="Doc_Ty" columns="15" />
        <dataField fieldName="Cstm_No" columns="15" />
        <dataField fieldName="Brn_No" columns="15" />
        <dataField fieldName="Doc_No" columns="15" />
        <dataField fieldName="Ln_No" columns="15" />
        <dataField fieldName="Itm_No" columns="15" />
        <dataField fieldName="ITEM" />
        <dataField fieldName="Unit_No" columns="15" />
        <dataField fieldName="UnitPrice" dataFormatString="c" columns="15" />
        <dataField fieldName="Quantity" dataFormatString="c" columns="15" />
        <dataField fieldName="Discount" columns="15" />
        <dataField fieldName="Titm_Sal" dataFormatString="c" columns="15" />
        <dataField fieldName="Titm_Cost" dataFormatString="c" columns="15" />
        <dataField fieldName="Itm_Cost" dataFormatString="c" columns="15" />
        <dataField fieldName="Catg_No" columns="15" />
        <dataField fieldName="Sup_No" columns="15" />
        <dataField fieldName="notesdtl" />
        <dataField fieldName="User_Id" columns="15" />
        <dataField fieldName="Idate" columns="10" />
        <dataField fieldName="Post" columns="15" />
      </dataFields>
    </view>
    <view id="editForm1" type="Form" commandId="command1" label="Review Qstpurdtl">
      <headerText>$DefaultEditViewDescription</headerText>
      <categories>
        <category id="c1" headerText="Qstpurdtl" flow="NewColumn"  newColumn="true">
          <description><![CDATA[$DefaultEditDescription]]></description>
          <dataFields>
            <dataField fieldName="Cstm_No" columns="15" />
            <dataField fieldName="Brn_No" columns="15" />
            <dataField fieldName="Doc_Ty" columns="15" />
            <dataField fieldName="Doc_No" columns="15" />
            <dataField fieldName="Ln_No" columns="15" />
            <dataField fieldName="Itm_No" columns="15" />
            <dataField fieldName="ITEM" />
            <dataField fieldName="Unit_No" columns="15" />
            <dataField fieldName="UnitPrice" dataFormatString="c" columns="15" />
            <dataField fieldName="Quantity" dataFormatString="c" columns="15" />
            <dataField fieldName="Discount" columns="15" />
            <dataField fieldName="Titm_Sal" dataFormatString="c" columns="15" />
            <dataField fieldName="Titm_Cost" dataFormatString="c" columns="15" />
            <dataField fieldName="Itm_Cost" dataFormatString="c" columns="15" />
            <dataField fieldName="Catg_No" columns="15" />
            <dataField fieldName="Sup_No" columns="15" />
            <dataField fieldName="notesdtl" />
            <dataField fieldName="User_Id" columns="15" />
            <dataField fieldName="Idate" columns="10" />
            <dataField fieldName="Post" columns="15" />
            <dataField fieldName="submit" columns="15" />
            <dataField fieldName="Cstm_NM" />
            <dataField fieldName="flat" columns="15" />
          </dataFields>
        </category>
      </categories>
    </view>
    <view id="createForm1" type="Form" commandId="command1" label="New Qstpurdtl">
      <headerText>$DefaultCreateViewDescription</headerText>
      <categories>
        <category id="c1" headerText="New Qstpurdtl" flow="NewColumn"  newColumn="true">
          <description><![CDATA[$DefaultNewDescription]]></description>
          <dataFields>
            <dataField fieldName="Cstm_No" columns="15" />
            <dataField fieldName="Brn_No" columns="15" />
            <dataField fieldName="Ln_No" columns="15" />
            <dataField fieldName="Itm_No" columns="15" />
            <dataField fieldName="ITEM" />
            <dataField fieldName="Unit_No" columns="15" />
            <dataField fieldName="Quantity" dataFormatString="c" columns="15" />
            <dataField fieldName="Discount" columns="15" />
            <dataField fieldName="Titm_Cost" dataFormatString="c" columns="15" />
            <dataField fieldName="Itm_Cost" dataFormatString="c" columns="15" />
            <dataField fieldName="notesdtl" />
            <dataField fieldName="Idate" columns="10" />
            <dataField fieldName="Post" columns="15" />
            <dataField fieldName="submit" columns="15" />
            <dataField fieldName="Cstm_NM" />
            <dataField fieldName="flat" columns="15" />
          </dataFields>
        </category>
      </categories>
    </view>
  </views>
  <actions>
    <actionGroup id="ag1" scope="Grid">
      <action id="a1" commandName="Select" commandArgument="editForm1" />
      <action id="a2" commandName="Edit" />
      <action id="a3" commandName="Delete" />
      <action id="a6" />
      <action id="a7" commandName="New" commandArgument="grid1" />
      <action id="a8" commandName="Duplicate" commandArgument="createForm1" />
      <action id="a9" />
      <action id="a10" commandName="BatchEdit" />
      <action id="a11" commandName="BatchEdit" commandArgument="editForm1" />
    </actionGroup>
    <actionGroup id="ag2" scope="Form">
      <action id="a1" commandName="Edit" />
      <action id="a2" commandName="Delete" />
      <action id="a3" commandName="Cancel" />
      <action id="a4" whenLastCommandName="Edit" commandName="Update" />
      <action id="a5" whenLastCommandName="Edit" commandName="Delete" />
      <action id="a6" whenLastCommandName="Edit" commandName="Cancel" />
      <action id="a7" whenLastCommandName="New" commandName="Insert" />
      <action id="a8" whenLastCommandName="New" commandName="Cancel" />
      <action id="a9" whenLastCommandName="Duplicate" commandName="Insert" />
      <action id="a10" whenLastCommandName="Duplicate" commandName="Cancel" />
      <action id="a11" whenLastCommandName="BatchEdit" commandName="Update" />
      <action id="a12" whenLastCommandName="BatchEdit" commandName="Cancel" />
      <action id="a13" whenLastCommandName="Insert" whenView="createForm1" commandName="Select" commandArgument="editForm1" whenKeySelected="true" whenClientScript="this.get_hasDetails()" />
    </actionGroup>
    <actionGroup id="ag3" scope="ActionBar" headerText="New" flat="true">
      <action id="a1" commandName="New" commandArgument="createForm1" cssClass="NewIcon" />
    </actionGroup>
    <actionGroup id="ag4" scope="ActionBar" headerText="Edit/Delete" flat="true">
      <action id="a1" whenKeySelected="true" commandName="Edit" commandArgument="editForm1" cssClass="EditIcon" whenView="grid1" />
      <action id="a2" whenKeySelected="true" commandName="Delete" cssClass="DeleteIcon" whenView="grid1" />
    </actionGroup>
    <actionGroup id="ag5" scope="ActionBar" headerText="Actions">
      <action id="a1" commandName="ExportCsv" />
      <action id="a2" />
      <action id="a3" commandName="ExportRowset" />
      <action id="a4" commandName="ExportRss" />
      <action id="a7" commandName="DataSheet" />
      <action id="a8" commandName="Grid" />
    </actionGroup>
    <actionGroup id="ag6" scope="ActionBar" headerText="Record">
      <action id="a1" whenLastCommandName="Edit" commandName="Update" />
      <action id="a2" whenLastCommandName="Edit" commandName="Cancel" />
      <action id="a3" whenLastCommandName="New" commandName="Insert" />
      <action id="a4" whenLastCommandName="New" commandName="Cancel" />
    </actionGroup>
    <actionGroup id="ag7" scope="ActionBar" headerText="Report">
      <action id="a1" commandName="ReportAsPdf" />
      <action id="a2" commandName="ReportAsImage" />
      <action id="a3" commandName="ReportAsExcel" />
      <action id="a4" commandName="ReportAsWord" />
    </actionGroup>
    <actionGroup id="ag8" scope="Row">
      <action id="a4" whenLastCommandName="Edit" commandName="Update" />
      <action id="a5" whenLastCommandName="Edit" commandName="Cancel" />
      <action id="a6" whenLastCommandName="New" commandName="Insert" />
      <action id="a7" whenLastCommandName="New" commandName="Cancel" />
      <action id="a8" whenLastCommandName="BatchEdit" commandName="Update" />
      <action id="a9" whenLastCommandName="BatchEdit" commandName="Cancel" />
    </actionGroup>
    <actionGroup id="ag9" scope="ActionColumn">
      <action id="a1" commandName="Edit" commandArgument="editForm1" />
      <action id="a2" commandName="Delete" />
    </actionGroup>
  </actions>
</dataController>